client.py
hello_world_cc4-0.0.9.dist-info/LICENSE
hello_world_cc4-0.0.9.dist-info/METADATA
hello_world_cc4-0.0.9.dist-info/WHEEL
hello_world_cc4-0.0.9.dist-info/top_level.txt
hello_world_cc4-0.0.9.dist-info/RECORD
